aranet4graph/__init__.py
aranet4_graph-0.4.dist-info/METADATA
aranet4_graph-0.4.dist-info/WHEEL
aranet4_graph-0.4.dist-info/entry_points.txt
aranet4_graph-0.4.dist-info/top_level.txt
aranet4_graph-0.4.dist-info/RECORD
