Metadata-Version: 2.1
Name: aranet4-graph
Version: 0.4
Summary: Graph data file(s) from an aranet4 sensor.
Home-page: https://github.com/hardaker/aranet4-graph
Author: Wes Hardaker
Author-email: opensource@hardakers.net
License: UNKNOWN
Platform: UNKNOWN
Classifier: Programming Language :: Python :: 3
Classifier: Operating System :: OS Independent
Requires-Python: >=3.6
Requires-Dist: pandas
Requires-Dist: seaborn
Requires-Dist: matplotlib
Requires-Dist: numpy
Requires-Dist: dateparser
